[
  {
    "id": 1,
    "name": "DALのバッグ",
    "checked": false,
    "variation": false
  },
  {
    "id": 2,
    "name": "アウトドアリュック",
    "checked": false,
    "variation": true,
    "colors": [
      { "id": 3, "name": "カーキ", "checked": false, "parentId": 2 },
      { "id": 4, "name": "オレンジ", "checked": false, "parentId": 2 },
      { "id": 5, "name": "ネイビー", "checked": false, "parentId": 2 }
    ]
  },
  {
    "id": 6,
    "name": "イースターなバッグ",
    "checked": false,
    "variation": false
  },
  {
    "id": 7,
    "name": "おおきめザック",
    "checked": false,
    "variation": true,
    "colors": [
      { "id": 8, "name": "レッド", "checked": false, "parentId": 7 },
      { "id": 9, "name": "グリーン", "checked": false, "parentId": 7 },
      { "id": 10, "name": "ブラック", "checked": false, "parentId": 7 },
      { "id": 11, "name": "ブルー", "checked": false, "parentId": 7 }
    ]
  },
  {
    "id": 12,
    "name": "おさかなポシェット",
    "checked": false,
    "variation": false
  },
  {
    "id": 13,
    "name": "かいがらポシェット",
    "checked": false,
    "variation": false
  },
  {
    "id": 14,
    "name": "くさあみリュック",
    "checked": false,
    "variation": false
  },
  {
    "id": 15,
    "name": "さくらのポシェット",
    "checked": false,
    "variation": false
  },
  {
    "id": 16,
    "name": "サコッシュ",
    "checked": false,
    "variation": true,
    "colors": [
      { "id": 17, "name": "ブルー", "checked": false, "parentId": 16 },
      { "id": 18, "name": "レッド", "checked": false, "parentId": 16 },
      { "id": 19, "name": "ブラック", "checked": false, "parentId": 16 }
    ]
  },
  {
    "id": 20,
    "name": "しかくいリュック",
    "checked": false,
    "variation": true,
    "colors": [
      { "id": 21, "name": "イエロー", "checked": false, "parentId": 20 },
      { "id": 22, "name": "ピンク", "checked": false, "parentId": 20 },
      { "id": 23, "name": "グリーン", "checked": false, "parentId": 20 }
    ]
  },
  {
    "id": 24,
    "name": "しょいこ",
    "checked": false,
    "variation": false
  },
  {
    "id": 25,
    "name": "スターなポシェット",
    "checked": false,
    "variation": false
  },
  {
    "id": 26,
    "name": "スタッズリュック",
    "checked": false,
    "variation": true,
    "colors": [
      { "id": 27, "name": "ブラック", "checked": false, "parentId": 26 },
      { "id": 28, "name": "ホワイト", "checked": false, "parentId": 26 }
    ]
  },
  {
    "id": 29,
    "name": "スノーフレークポシェット",
    "checked": false,
    "variation": false
  },
  {
    "id": 30,
    "name": "スポーツバッグ",
    "checked": false,
    "variation": true,
    "colors": [
      { "id": 31, "name": "ブルー", "checked": false, "parentId": 30 },
      { "id": 32, "name": "レッド", "checked": false, "parentId": 30 },
      { "id": 33, "name": "ブラック", "checked": false, "parentId": 30 }
    ]
  },
  {
    "id": 34,
    "name": "せおいばしご",
    "checked": false,
    "variation": false
  }
]