[
  {
    "id": 1,
    "name": "１ばんだまのふく",
    "checked": false,
    "variation": false
  },
  {
    "id": 2,
    "name": "２ばんだまのふく",
    "checked": false,
    "variation": false
  },
  {
    "id": 3,
    "name": "３ばんだまのふく",
    "checked": false,
    "variation": false
  },
  {
    "id": 4,
    "name": "４ばんだまのふく",
    "checked": false,
    "variation": false
  },
  {
    "id": 5,
    "name": "５ばんだまのふく",
    "checked": false,
    "variation": false
  },
  {
    "id": 6,
    "name": "６ばんだまのふく",
    "checked": false,
    "variation": false
  },
  {
    "id": 7,
    "name": "７ばんだまのふく",
    "checked": false,
    "variation": false
  },
  {
    "id": 8,
    "name": "８ばんだまのふく",
    "checked": false,
    "variation": false
  },
  {
    "id": 9,
    "name": "９ばんだまのふく",
    "checked": false,
    "variation": false
  },
  {
    "id": 10,
    "name": "DALエプロン",
    "checked": false,
    "variation": false
  },
  {
    "id": 11,
    "name": "DALのMA‐1",
    "checked": false,
    "variation": false
  },
  {
    "id": 12,
    "name": "DALのＴシャツ",
    "checked": false,
    "variation": false
  },
  {
    "id": 13,
    "name": "MA‐1",
    "checked": false,
    "variation": true,
    "colors": [
      { "id": 14, "name": "カーキ", "checked": false, "parentId": 13 },
      { "id": 15, "name": "ブラック", "checked": false, "parentId": 13 },
      { "id": 16, "name": "ブルー", "checked": false, "parentId": 13 },
      { "id": 17, "name": "ブラウン", "checked": false, "parentId": 13 }
    ]
  },
  {
    "id": 18,
    "name": "MVPなTシャツ",
    "checked": false,
    "variation": false
  },
  {
    "id": 19,
    "name": "No.1のふく",
    "checked": false,
    "variation": false
  },
  {
    "id": 20,
    "name": "No.2のふく",
    "checked": false,
    "variation": false
  },
  {
    "id": 21,
    "name": "No.3のふく",
    "checked": false,
    "variation": false
  },
  {
    "id": 22,
    "name": "No.4のふく",
    "checked": false,
    "variation": false
  },
  {
    "id": 23,
    "name": "OKモータースジャケット",
    "checked": false,
    "variation": false
  },
  {
    "id": 24,
    "name": "Vネックセーター",
    "checked": false,
    "variation": true,
    "colors": [
      { "id": 25, "name": "ブルー", "checked": false, "parentId": 24 },
      { "id": 26, "name": "レッド", "checked": false, "parentId": 24 },
      { "id": 27, "name": "ブラック", "checked": false, "parentId": 24 }
    ]
  },
  {
    "id": 28,
    "name": "アーガイルのセーター",
    "checked": false,
    "variation": true,
    "colors": [
      { "id": 29, "name": "グリーン", "checked": false, "parentId": 28 },
      { "id": 30, "name": "グレー", "checked": false, "parentId": 28 },
      { "id": 31, "name": "マスタード", "checked": false, "parentId": 28 },
      { "id": 32, "name": "ブラック", "checked": false, "parentId": 28 },
      { "id": 33, "name": "レッド", "checked": false, "parentId": 28 },
      { "id": 34, "name": "パープル", "checked": false, "parentId": 28 },
      { "id": 35, "name": "ピンク", "checked": false, "parentId": 28 },
      { "id": 36, "name": "ホワイト", "checked": false, "parentId": 28 }
    ]
  },
  {
    "id": 37,
    "name": "アーガイルベスト",
    "checked": false,
    "variation": true,
    "colors": [
      { "id": 38, "name": "ブルー", "checked": false, "parentId": 37 },
      { "id": 39, "name": "ピンク", "checked": false, "parentId": 37 },
      { "id": 40, "name": "ブラウン", "checked": false, "parentId": 37 },
      { "id": 41, "name": "レッド", "checked": false, "parentId": 37 },
      { "id": 42, "name": "グレー", "checked": false, "parentId": 37 },
      { "id": 43, "name": "グリーン", "checked": false, "parentId": 37 }
    ]
  },
  {
    "id": 44,
    "name": "アームプリントTシャツ",
    "checked": false,
    "variation": true,
    "colors": [
      { "id": 45, "name": "オレンジ", "checked": false, "parentId": 44 },
      { "id": 46, "name": "ホワイト", "checked": false, "parentId": 44 },
      { "id": 47, "name": "ブラック", "checked": false, "parentId": 44 }
    ]
  },
  {
    "id": 48,
    "name": "アノラック",
    "checked": false,
    "variation": true,
    "colors": [
      { "id": 49, "name": "キャメル", "checked": false, "parentId": 48 },
      { "id": 50, "name": "レッド", "checked": false, "parentId": 48 },
      { "id": 51, "name": "ブルー", "checked": false, "parentId": 48 }
    ]
  },
  {
    "id": 52,
    "name": "アメフトシャツ",
    "checked": false,
    "variation": true,
    "colors": [
      { "id": 53, "name": "グリーン", "checked": false, "parentId": 52 },
      { "id": 54, "name": "ホワイト", "checked": false, "parentId": 52 },
      { "id": 55, "name": "イエロー", "checked": false, "parentId": 52 },
      { "id": 56, "name": "ワインレッド", "checked": false, "parentId": 52 },
      { "id": 57, "name": "ブルー", "checked": false, "parentId": 52 },
      { "id": 58, "name": "ターコイズ", "checked": false, "parentId": 52 },
      { "id": 59, "name": "レッド", "checked": false, "parentId": 52 },
      { "id": 60, "name": "ブラック", "checked": false, "parentId": 52 }
    ]
  },
  {
    "id": 61,
    "name": "アランカーディガン",
    "checked": false,
    "variation": true,
    "colors": [
      { "id": 62, "name": "ベージュ", "checked": false, "parentId": 61 },
      { "id": 63, "name": "ライトブルー", "checked": false, "parentId": 61 },
      { "id": 64, "name": "ピンク", "checked": false, "parentId": 61 },
      { "id": 65, "name": "イエロー", "checked": false, "parentId": 61 }
    ]
  },
  {
    "id": 66,
    "name": "アランセーター",
    "checked": false,
    "variation": true,
    "colors": [
      { "id": 67, "name": "レッド", "checked": false, "parentId": 66 },
      { "id": 68, "name": "ホワイト", "checked": false, "parentId": 66 },
      { "id": 69, "name": "グレー", "checked": false, "parentId": 66 },
      { "id": 70, "name": "グリーン", "checked": false, "parentId": 66 },
      { "id": 71, "name": "ブラック", "checked": false, "parentId": 66 },
      { "id": 72, "name": "オレンジ", "checked": false, "parentId": 66 },
      { "id": 73, "name": "ブルー", "checked": false, "parentId": 66 }
    ]
  },
  {
    "id": 74,
    "name": "あんないがかりのふく",
    "checked": false,
    "variation": true,
    "colors": [
      { "id": 75, "name": "グリーン", "checked": false, "parentId": 74 },
      { "id": 76, "name": "レッド", "checked": false, "parentId": 74 },
      { "id": 77, "name": "イエロー", "checked": false, "parentId": 74 }
    ]
  },
  {
    "id": 78,
    "name": "アンニョンTシャツ",
    "checked": false,
    "variation": false
  },
  {
    "id": 79,
    "name": "いたまえのふく",
    "checked": false,
    "variation": true,
    "colors": [
      { "id": 80, "name": "しろ", "checked": false, "parentId": 79 },
      { "id": 81, "name": "こん", "checked": false, "parentId": 79 }
    ]
  },
  {
    "id": 82,
    "name": "いちばんぼしのふく",
    "checked": false,
    "variation": false
  },
  {
    "id": 83,
    "name": "イヤフォンコーデ",
    "checked": false,
    "variation": true,
    "colors": [
      { "id": 84, "name": "ブラウン", "checked": false, "parentId": 83 },
      { "id": 85, "name": "グリーン", "checked": false, "parentId": 83 },
      { "id": 86, "name": "ブルー", "checked": false, "parentId": 83 },
      { "id": 87, "name": "イエロー", "checked": false, "parentId": 83 }
    ]
  },
  {
    "id": 88,
    "name": "インセクトアロハ",
    "checked": false,
    "variation": false
  },
  {
    "id": 89,
    "name": "ヴァンパイアのふく",
    "checked": false,
    "variation": true,
    "colors": [
      { "id": 90, "name": "ブラック", "checked": false, "parentId": 89 },
      { "id": 91, "name": "パープル", "checked": false, "parentId": 89 }
    ]
  },
  {
    "id": 92,
    "name": "ウェスタンなふく",
    "checked": false,
    "variation": true,
    "colors": [
      { "id": 93, "name": "ブルー", "checked": false, "parentId": 92 },
      { "id": 94, "name": "ピンク", "checked": false, "parentId": 92 },
      { "id": 95, "name": "イエロー", "checked": false, "parentId": 92 },
      { "id": 96, "name": "ブラック", "checked": false, "parentId": 92 }
    ]
  },
  {
    "id": 97,
    "name": "うさぎのTシャツ",
    "checked": false,
    "variation": false
  },
  {
    "id": 98,
    "name": "うでカバーつきエプロン",
    "checked": false,
    "variation": true,
    "colors": [
      { "id": 99, "name": "ピンク", "checked": false, "parentId": 98 },
      { "id": 100, "name": "ブルー", "checked": false, "parentId": 98 },
      { "id": 101, "name": "オレンジ", "checked": false, "parentId": 98 },
      { "id": 102, "name": "グリーン", "checked": false, "parentId": 98 },
      { "id": 103, "name": "パープル", "checked": false, "parentId": 98 }
    ]
  },
  {
    "id": 104,
    "name": "うみのはんてん",
    "checked": false,
    "variation": true,
    "colors": [
      { "id": 105, "name": "こん", "checked": false, "parentId": 104 },
      { "id": 106, "name": "あお", "checked": false, "parentId": 104 }
    ]
  },
  {
    "id": 107,
    "name": "エースのTシャツ",
    "checked": false,
    "variation": false
  },
  {
    "id": 108,
    "name": "えいじTシャツ",
    "checked": false,
    "variation": true,
    "colors": [
      { "id": 109, "name": "ブラック", "checked": false, "parentId": 108 },
      { "id": 110, "name": "ホワイト", "checked": false, "parentId": 108 },
      { "id": 111, "name": "レッド", "checked": false, "parentId": 108 }
    ]
  },
  {
    "id": 112,
    "name": "えきでんなふく",
    "checked": false,
    "variation": true,
    "colors": [
      { "id": 113, "name": "ブルー", "checked": false, "parentId": 112 },
      { "id": 114, "name": "ライトブルー", "checked": false, "parentId": 112 },
      { "id": 115, "name": "パープル", "checked": false, "parentId": 112 },
      { "id": 116, "name": "ブラック", "checked": false, "parentId": 112 },
      { "id": 117, "name": "オレンジ", "checked": false, "parentId": 112 },
      { "id": 118, "name": "グリーン", "checked": false, "parentId": 112 },
      { "id": 119, "name": "レッド", "checked": false, "parentId": 112 },
      { "id": 120, "name": "ホワイト", "checked": false, "parentId": 112 }
    ]
  },
  {
    "id": 121,
    "name": "エプロン",
    "checked": false,
    "variation": true,
    "colors": [
      { "id": 122, "name": "オレンジ", "checked": false, "parentId": 121 },
      { "id": 123, "name": "グリーン", "checked": false, "parentId": 121 },
      { "id": 124, "name": "ブルー", "checked": false, "parentId": 121 },
      { "id": 125, "name": "ピンク", "checked": false, "parentId": 121 },
      { "id": 126, "name": "ライトブルー", "checked": false, "parentId": 121 },
      { "id": 127, "name": "パープル", "checked": false, "parentId": 121 },
      { "id": 128, "name": "グレー", "checked": false, "parentId": 121 },
      { "id": 129, "name": "ブラウン", "checked": false, "parentId": 121 }
    ]
  },
  {
    "id": 130,
    "name": "えんびふく",
    "checked": false,
    "variation": true,
    "colors": [
      { "id": 131, "name": "ブラック", "checked": false, "parentId": 130 },
      { "id": 132, "name": "ホワイト", "checked": false, "parentId": 130 }
    ]
  },
  {
    "id": 133,
    "name": "オーバーストライプシャツ",
    "checked": false,
    "variation": true,
    "colors": [
      { "id": 134, "name": "ブルー", "checked": false, "parentId": 133 },
      { "id": 135, "name": "パープル", "checked": false, "parentId": 133 },
      { "id": 136, "name": "ピンク", "checked": false, "parentId": 133 },
      { "id": 137, "name": "グリーン", "checked": false, "parentId": 133 },
      { "id": 138, "name": "グレー", "checked": false, "parentId": 133 },
      { "id": 139, "name": "ベージュ", "checked": false, "parentId": 133 },
      { "id": 140, "name": "オレンジ", "checked": false, "parentId": 133 }
    ]
  },
  {
    "id": 141,
    "name": "オイルスキンのジャケット",
    "checked": false,
    "variation": true,
    "colors": [
      { "id": 142, "name": "イエロー", "checked": false, "parentId": 141 },
      { "id": 143, "name": "レッド", "checked": false, "parentId": 141 },
      { "id": 144, "name": "グレー", "checked": false, "parentId": 141 }
    ]
  },
  {
    "id": 145,
    "name": "おうさまのふく",
    "checked": false,
    "variation": false
  },
  {
    "id": 146,
    "name": "おうじさまシャツ",
    "checked": false,
    "variation": true,
    "colors": [
      { "id": 147, "name": "ホワイト", "checked": false, "parentId": 146 },
      { "id": 148, "name": "ブラック", "checked": false, "parentId": 146 },
      { "id": 149, "name": "ピンク", "checked": false, "parentId": 146 },
      { "id": 150, "name": "ブルー", "checked": false, "parentId": 146 },
      { "id": 151, "name": "クリーム", "checked": false, "parentId": 146 }
    ]
  },
  {
    "id": 152,
    "name": "おおばんストールTシャツ",
    "checked": false,
    "variation": true,
    "colors": [
      { "id": 153, "name": "ブラウン", "checked": false, "parentId": 152 },
      { "id": 154, "name": "ピンク", "checked": false, "parentId": 152 },
      { "id": 155, "name": "グレー", "checked": false, "parentId": 152 }
    ]
  },
  {
    "id": 156,
    "name": "オラTシャツ",
    "checked": false,
    "variation": false
  },
  {
    "id": 157,
    "name": "カーディガン&シャツ",
    "checked": false,
    "variation": true,
    "colors": [
      { "id": 158, "name": "イエロー", "checked": false, "parentId": 157 },
      { "id": 159, "name": "ミント", "checked": false, "parentId": 157 },
      { "id": 160, "name": "ピンク", "checked": false, "parentId": 157 },
      { "id": 161, "name": "ブルー", "checked": false, "parentId": 157 },
      { "id": 162, "name": "グレー", "checked": false, "parentId": 157 },
      { "id": 163, "name": "ブラック", "checked": false, "parentId": 157 }
    ]
  },
  {
    "id": 164,
    "name": "かいきんシャツ",
    "checked": false,
    "variation": true,
    "colors": [
      { "id": 165, "name": "コーラル", "checked": false, "parentId": 164 },
      { "id": 166, "name": "ブルー", "checked": false, "parentId": 164 },
      { "id": 167, "name": "グリーン", "checked": false, "parentId": 164 },
      { "id": 168, "name": "ベージュ", "checked": false, "parentId": 164 }
    ]
  },
  {
    "id": 169,
    "name": "かいぞくのコート",
    "checked": false,
    "variation": true,
    "colors": [
      { "id": 170, "name": "レッド", "checked": false, "parentId": 169 },
      { "id": 171, "name": "ブルー", "checked": false, "parentId": 169 },
      { "id": 172, "name": "ブラック", "checked": false, "parentId": 169 }
    ]
  },
  {
    "id": 173,
    "name": "かいとうのふく",
    "checked": false,
    "variation": false
  },
  {
    "id": 174,
    "name": "カウボーイシャツ",
    "checked": false,
    "variation": true,
    "colors": [
      { "id": 175, "name": "ホワイト", "checked": false, "parentId": 174 },
      { "id": 176, "name": "レッド", "checked": false, "parentId": 174 },
      { "id": 177, "name": "ブルー", "checked": false, "parentId": 174 },
      { "id": 178, "name": "ライトブルー", "checked": false, "parentId": 174 },
      { "id": 179, "name": "ブラウン", "checked": false, "parentId": 174 }
    ]
  },
  {
    "id": 180,
    "name": "ガウンコート",
    "checked": false,
    "variation": true,
    "colors": [
      { "id": 181, "name": "ブラウン", "checked": false, "parentId": 180 },
      { "id": 182, "name": "ブラック", "checked": false, "parentId": 180 },
      { "id": 183, "name": "ブルー", "checked": false, "parentId": 180 },
      { "id": 184, "name": "レッド", "checked": false, "parentId": 180 }
    ]
  },
  {
    "id": 185,
    "name": "かえるのTシャツ",
    "checked": false,
    "variation": false
  },
  {
    "id": 186,
    "name": "がくしのふく",
    "checked": false,
    "variation": true,
    "colors": [
      { "id": 187, "name": "レッド", "checked": false, "parentId": 186 },
      { "id": 188, "name": "グリーン", "checked": false, "parentId": 186 },
      { "id": 189, "name": "ブルー", "checked": false, "parentId": 186 },
      { "id": 190, "name": "イエロー", "checked": false, "parentId": 186 }
    ]
  },
  {
    "id": 191,
    "name": "がくせいふく",
    "checked": false,
    "variation": true,
    "colors": [
      { "id": 192, "name": "ブラック", "checked": false, "parentId": 191 },
      { "id": 193, "name": "ワインレッド", "checked": false, "parentId": 191 },
      { "id": 194, "name": "グリーン", "checked": false, "parentId": 191 },
      { "id": 195, "name": "ホワイト", "checked": false, "parentId": 191 },
      { "id": 196, "name": "パープル", "checked": false, "parentId": 191 },
      { "id": 197, "name": "グレー", "checked": false, "parentId": 191 },
      { "id": 198, "name": "ブルー", "checked": false, "parentId": 191 }
    ]
  },
  {
    "id": 199,
    "name": "かさねぎTシャツ",
    "checked": false,
    "variation": true,
    "colors": [
      { "id": 200, "name": "ネイビー", "checked": false, "parentId": 199 },
      { "id": 201, "name": "ホワイト", "checked": false, "parentId": 199 },
      { "id": 202, "name": "グリーン", "checked": false, "parentId": 199 },
      { "id": 203, "name": "オレンジ", "checked": false, "parentId": 199 }
    ]
  },
  {
    "id": 204,
    "name": "かさねぎプリントTシャツ",
    "checked": false,
    "variation": true,
    "colors": [
      { "id": 205, "name": "ブラック", "checked": false, "parentId": 204 },
      { "id": 206, "name": "イエロー", "checked": false, "parentId": 204 },
      { "id": 207, "name": "ホワイト", "checked": false, "parentId": 204 }
    ]
  },
  {
    "id": 208,
    "name": "かすみのふく",
    "checked": false,
    "variation": false
  },
  {
    "id": 209,
    "name": "かっちゅう",
    "checked": false,
    "variation": true,
    "colors": [
      { "id": 210, "name": "あか", "checked": false, "parentId": 209 },
      { "id": 211, "name": "くろ", "checked": false, "parentId": 209 },
      { "id": 212, "name": "あお", "checked": false, "parentId": 209 },
      { "id": 213, "name": "しろ", "checked": false, "parentId": 209 },
      { "id": 214, "name": "やまぶきいろ", "checked": false, "parentId": 209 }
    ]
  },
  {
    "id": 215,
    "name": "カバーオール",
    "checked": false,
    "variation": true,
    "colors": [
      { "id": 216, "name": "カーキ", "checked": false, "parentId": 215 },
      { "id": 217, "name": "ネイビー", "checked": false, "parentId": 215 },
      { "id": 218, "name": "ベージュ", "checked": false, "parentId": 215 },
      { "id": 219, "name": "レッド", "checked": false, "parentId": 215 }
    ]
  },
  {
    "id": 220,
    "name": "カフェのせいふく",
    "checked": false,
    "variation": true,
    "colors": [
      { "id": 221, "name": "ブラック", "checked": false, "parentId": 220 },
      { "id": 222, "name": "グリーン", "checked": false, "parentId": 220 },
      { "id": 223, "name": "レッド", "checked": false, "parentId": 220 },
      { "id": 224, "name": "ブラウン", "checked": false, "parentId": 220 }
    ]
  },
  {
    "id": 225,
    "name": "カメラつきワイシャツ",
    "checked": false,
    "variation": true,
    "colors": [
      { "id": 226, "name": "ライトブルー", "checked": false, "parentId": 225 },
      { "id": 227, "name": "ブラック", "checked": false, "parentId": 225 }
    ]
  },
  {
    "id": 228,
    "name": "がらものフリース",
    "checked": false,
    "variation": true,
    "colors": [
      { "id": 229, "name": "モスグリーン", "checked": false, "parentId": 228 },
      { "id": 230, "name": "ブルー", "checked": false, "parentId": 228 },
      { "id": 231, "name": "ブラウン", "checked": false, "parentId": 228 },
      { "id": 232, "name": "パープル", "checked": false, "parentId": 228 },
      { "id": 233, "name": "グリーン", "checked": false, "parentId": 228 }
    ]
  },
  {
    "id": 234,
    "name": "カレッジカーディガン",
    "checked": false,
    "variation": true,
    "colors": [
      { "id": 235, "name": "ネイビー", "checked": false, "parentId": 234 },
      { "id": 236, "name": "レッド", "checked": false, "parentId": 234 },
      { "id": 237, "name": "グレー", "checked": false, "parentId": 234 },
      { "id": 238, "name": "オレンジ", "checked": false, "parentId": 234 },
      { "id": 239, "name": "ホワイト", "checked": false, "parentId": 234 }
    ]
  },
  {
    "id": 240,
    "name": "かんごしのジャケット",
    "checked": false,
    "variation": true,
    "colors": [
      { "id": 241, "name": "ブルー", "checked": false, "parentId": 240 },
      { "id": 242, "name": "ホワイト", "checked": false, "parentId": 240 },
      { "id": 243, "name": "ピンク", "checked": false, "parentId": 240 }
    ]
  },
  {
    "id": 244,
    "name": "かんじTシャツ",
    "checked": false,
    "variation": true,
    "colors": [
      { "id": 245, "name": "グリーン", "checked": false, "parentId": 244 },
      { "id": 246, "name": "ピンク", "checked": false, "parentId": 244 },
      { "id": 247, "name": "ブルー", "checked": false, "parentId": 244 },
      { "id": 248, "name": "ブラック", "checked": false, "parentId": 244 }
    ]
  },
  {
    "id": 249,
    "name": "カンフーなふく",
    "checked": false,
    "variation": true,
    "colors": [
      { "id": 250, "name": "ネイビー", "checked": false, "parentId": 249 },
      { "id": 251, "name": "ホワイト", "checked": false, "parentId": 249 },
      { "id": 252, "name": "ライトブルー", "checked": false, "parentId": 249 },
      { "id": 253, "name": "イエロー", "checked": false, "parentId": 249 },
      { "id": 254, "name": "グリーン", "checked": false, "parentId": 249 }
    ]
  },
  {
    "id": 255,
    "name": "ギザギザのTシャツ",
    "checked": false,
    "variation": false
  },
  {
    "id": 256,
    "name": "きぞくのコート",
    "checked": false,
    "variation": true,
    "colors": [
      { "id": 257, "name": "グリーン", "checked": false, "parentId": 256 },
      { "id": 258, "name": "ルージュ", "checked": false, "parentId": 256 },
      { "id": 259, "name": "ホワイト", "checked": false, "parentId": 256 },
      { "id": 260, "name": "ブルー", "checked": false, "parentId": 256 },
      { "id": 261, "name": "ブラック", "checked": false, "parentId": 256 },
      { "id": 262, "name": "パープル", "checked": false, "parentId": 256 },
      { "id": 263, "name": "イエロー", "checked": false, "parentId": 256 },
      { "id": 264, "name": "レッド", "checked": false, "parentId": 256 }
    ]
  },
  {
    "id": 265,
    "name": "きのセーター",
    "checked": false,
    "variation": false
  },
  {
    "id": 266,
    "name": "キャリアなジャケット",
    "checked": false,
    "variation": true,
    "colors": [
      { "id": 267, "name": "グレー", "checked": false, "parentId": 266 },
      { "id": 268, "name": "ベージュ", "checked": false, "parentId": 266 },
      { "id": 269, "name": "ピーチ", "checked": false, "parentId": 266 },
      { "id": 270, "name": "ライトブルー", "checked": false, "parentId": 266 },
      { "id": 271, "name": "ピンク", "checked": false, "parentId": 266 },
      { "id": 272, "name": "グリーン", "checked": false, "parentId": 266 },
      { "id": 273, "name": "ブルー", "checked": false, "parentId": 266 },
      { "id": 274, "name": "レッド", "checked": false, "parentId": 266 }
    ]
  },
  {
    "id": 275,
    "name": "キャンパーのTシャツ",
    "checked": false,
    "variation": false
  },
  {
    "id": 276,
    "name": "キューバシャツ",
    "checked": false,
    "variation": true,
    "colors": [
      { "id": 277, "name": "グリーン", "checked": false, "parentId": 276 },
      { "id": 278, "name": "レッド", "checked": false, "parentId": 276 },
      { "id": 279, "name": "ブラウン", "checked": false, "parentId": 276 },
      { "id": 280, "name": "ブルー", "checked": false, "parentId": 276 }
    ]
  },
  {
    "id": 281,
    "name": "キルティングジャケット",
    "checked": false,
    "variation": true,
    "colors": [
      { "id": 282, "name": "ピンク", "checked": false, "parentId": 281 },
      { "id": 283, "name": "ブラウン", "checked": false, "parentId": 281 },
      { "id": 284, "name": "ライム", "checked": false, "parentId": 281 },
      { "id": 285, "name": "ブルー", "checked": false, "parentId": 281 },
      { "id": 286, "name": "グリーン", "checked": false, "parentId": 281 }
    ]
  },
  {
    "id": 287,
    "name": "キルティングダウン",
    "checked": false,
    "variation": true,
    "colors": [
      { "id": 288, "name": "ネイビー", "checked": false, "parentId": 287 },
      { "id": 289, "name": "グレー", "checked": false, "parentId": 287 },
      { "id": 290, "name": "グリーン", "checked": false, "parentId": 287 },
      { "id": 291, "name": "パープル", "checked": false, "parentId": 287 },
      { "id": 292, "name": "オリーブ", "checked": false, "parentId": 287 }
    ]
  },
  {
    "id": 293,
    "name": "ギンガムチェックのシャツ",
    "checked": false,
    "variation": true,
    "colors": [
      { "id": 294, "name": "レッド", "checked": false, "parentId": 293 },
      { "id": 295, "name": "グリーン", "checked": false, "parentId": 293 },
      { "id": 296, "name": "ブルー", "checked": false, "parentId": 293 },
      { "id": 297, "name": "グレー", "checked": false, "parentId": 293 },
      { "id": 298, "name": "オレンジ", "checked": false, "parentId": 293 },
      { "id": 299, "name": "ピンク", "checked": false, "parentId": 293 },
      { "id": 300, "name": "パープル", "checked": false, "parentId": 293 },
      { "id": 301, "name": "ライトブルー", "checked": false, "parentId": 293 }
    ]
  },
  {
    "id": 302,
    "name": "くまのTシャツ",
    "checked": false,
    "variation": false
  },
  {
    "id": 303,
    "name": "クリスマスセーター",
    "checked": false,
    "variation": true,
    "colors": [
      { "id": 304, "name": "グリーン", "checked": false, "parentId": 303 },
      { "id": 305, "name": "レッド", "checked": false, "parentId": 303 },
      { "id": 306, "name": "ブルー", "checked": false, "parentId": 303 }
    ]
  },
  {
    "id": 307,
    "name": "クルタ",
    "checked": false,
    "variation": true,
    "colors": [
      { "id": 308, "name": "グリーン", "checked": false, "parentId": 307 },
      { "id": 309, "name": "グレー", "checked": false, "parentId": 307 },
      { "id": 310, "name": "ブルー", "checked": false, "parentId": 307 },
      { "id": 311, "name": "ベージュ", "checked": false, "parentId": 307 }
    ]
  },
  {
    "id": 312,
    "name": "ケイトのカットソー",
    "checked": false,
    "variation": true,
    "colors": [
      { "id": 313, "name": "トワイライト", "checked": false, "parentId": 312 },
      { "id": 314, "name": "ミッドナイト", "checked": false, "parentId": 312 },
      { "id": 315, "name": "パッション", "checked": false, "parentId": 312 },
      { "id": 316, "name": "オーシャン", "checked": false, "parentId": 312 },
      { "id": 317, "name": "サンセット", "checked": false, "parentId": 312 },
      { "id": 318, "name": "ラブ", "checked": false, "parentId": 312 }
    ]
  },
  {
    "id": 319,
    "name": "ケイトのコート",
    "checked": false,
    "variation": true,
    "colors": [
      { "id": 320, "name": "トワイライト", "checked": false, "parentId": 319 },
      { "id": 321, "name": "ミッドナイト", "checked": false, "parentId": 319 },
      { "id": 322, "name": "パッション", "checked": false, "parentId": 319 },
      { "id": 323, "name": "オーシャン", "checked": false, "parentId": 319 },
      { "id": 324, "name": "サンセット", "checked": false, "parentId": 319 },
      { "id": 325, "name": "ラブ", "checked": false, "parentId": 319 }
    ]
  },
  {
    "id": 326,
    "name": "けっしょうのセーター",
    "checked": false,
    "variation": true,
    "colors": [
      { "id": 327, "name": "ブルー", "checked": false, "parentId": 326 },
      { "id": 328, "name": "ライトブルー", "checked": false, "parentId": 326 }
    ]
  },
  {
    "id": 329,
    "name": "ケミカルデニムジャケット",
    "checked": false,
    "variation": true,
    "colors": [
      { "id": 330, "name": "ブルー", "checked": false, "parentId": 329 },
      { "id": 331, "name": "ブラック", "checked": false, "parentId": 329 }
    ]
  },
  {
    "id": 332,
    "name": "コーチジャケット",
    "checked": false,
    "variation": true,
    "colors": [
      { "id": 333, "name": "ブラック", "checked": false, "parentId": 332 },
      { "id": 334, "name": "グリーン", "checked": false, "parentId": 332 },
      { "id": 335, "name": "ブルー", "checked": false, "parentId": 332 },
      { "id": 336, "name": "レッド", "checked": false, "parentId": 332 }
    ]
  },
  {
    "id": 337,
    "name": "コーディガン",
    "checked": false,
    "variation": true,
    "colors": [
      { "id": 338, "name": "パープル", "checked": false, "parentId": 337 },
      { "id": 339, "name": "ピンク", "checked": false, "parentId": 337 },
      { "id": 340, "name": "ライトブルー", "checked": false, "parentId": 337 },
      { "id": 341, "name": "グレー", "checked": false, "parentId": 337 },
      { "id": 342, "name": "グリーン", "checked": false, "parentId": 337 }
    ]
  },
  {
    "id": 343,
    "name": "ゴールドプリントTシャツ",
    "checked": false,
    "variation": true,
    "colors": [
      { "id": 344, "name": "ブラック", "checked": false, "parentId": 343 },
      { "id": 345, "name": "ホワイト", "checked": false, "parentId": 343 }
    ]
  },
  {
    "id": 346,
    "name": "こうつうゆうどうのふく",
    "checked": false,
    "variation": true,
    "colors": [
      { "id": 347, "name": "ブラック", "checked": false, "parentId": 346 },
      { "id": 348, "name": "オレンジ", "checked": false, "parentId": 346 }
    ]
  },
  {
    "id": 349,
    "name": "こしまきシャツ",
    "checked": false,
    "variation": true,
    "colors": [
      { "id": 350, "name": "イエロー", "checked": false, "parentId": 349 },
      { "id": 351, "name": "ブルー", "checked": false, "parentId": 349 },
      { "id": 352, "name": "レッド", "checked": false, "parentId": 349 }
    ]
  },
  {
    "id": 353,
    "name": "コックさんのふく",
    "checked": false,
    "variation": true,
    "colors": [
      { "id": 354, "name": "レッド", "checked": false, "parentId": 353 },
      { "id": 355, "name": "ブルー", "checked": false, "parentId": 353 },
      { "id": 356, "name": "グリーン", "checked": false, "parentId": 353 },
      { "id": 357, "name": "イエロー", "checked": false, "parentId": 353 },
      { "id": 358, "name": "オレンジ", "checked": false, "parentId": 353 },
      { "id": 359, "name": "ブラウン", "checked": false, "parentId": 353 },
      { "id": 360, "name": "ブラック", "checked": false, "parentId": 353 }
    ]
  },
  {
    "id": 361,
    "name": "ゴムエプロン",
    "checked": false,
    "variation": true,
    "colors": [
      { "id": 362, "name": "ブラック", "checked": false, "parentId": 361 },
      { "id": 363, "name": "ホワイト", "checked": false, "parentId": 361 }
    ]
  },
  {
    "id": 364,
    "name": "コメディアンなふく",
    "checked": false,
    "variation": true,
    "colors": [
      { "id": 365, "name": "オレンジ", "checked": false, "parentId": 364 },
      { "id": 366, "name": "ブルー", "checked": false, "parentId": 364 },
      { "id": 367, "name": "レッド", "checked": false, "parentId": 364 },
      { "id": 368, "name": "イエロー", "checked": false, "parentId": 364 },
      { "id": 369, "name": "グリーン", "checked": false, "parentId": 364 },
      { "id": 370, "name": "パープル", "checked": false, "parentId": 364 },
      { "id": 371, "name": "エメラルド", "checked": false, "parentId": 364 },
      { "id": 372, "name": "ホワイト", "checked": false, "parentId": 364 }
    ]
  },
  {
    "id": 373,
    "name": "こんにちはTシャツ",
    "checked": false,
    "variation": false
  },
  {
    "id": 374,
    "name": "サイクルジャージ",
    "checked": false,
    "variation": true,
    "colors": [
      { "id": 375, "name": "ブルー×ホワイト", "checked": false, "parentId": 374 },
      { "id": 376, "name": "ブラック×ブルー", "checked": false, "parentId": 374 },
      { "id": 377, "name": "ブラック×レッド", "checked": false, "parentId": 374 },
      { "id": 378, "name": "イエロー×ブラック", "checked": false, "parentId": 374 },
      { "id": 379, "name": "レッド×グリーン", "checked": false, "parentId": 374 },
      { "id": 380, "name": "レッド×オレンジ", "checked": false, "parentId": 374 },
      { "id": 381, "name": "ライム×ライトブルー", "checked": false, "parentId": 374 },
      { "id": 382, "name": "パープル×ピンク", "checked": false, "parentId": 374 }
    ]
  },
  {
    "id": 383,
    "name": "サイケデリックシャツ",
    "checked": false,
    "variation": true,
    "colors": [
      { "id": 384, "name": "オレンジ", "checked": false, "parentId": 383 },
      { "id": 385, "name": "グリーン", "checked": false, "parentId": 383 },
      { "id": 386, "name": "レッド", "checked": false, "parentId": 383 }
    ]
  },
  {
    "id": 387,
    "name": "さかなTシャツ",
    "checked": false,
    "variation": false
  },
  {
    "id": 388,
    "name": "さぎょうふく",
    "checked": false,
    "variation": true,
    "colors": [
      { "id": 389, "name": "ライトブルー", "checked": false, "parentId": 388 },
      { "id": 390, "name": "ベージュ", "checked": false, "parentId": 388 },
      { "id": 391, "name": "ネイビー", "checked": false, "parentId": 388 }
    ]
  },
  {
    "id": 392,
    "name": "サッカーのユニフォーム",
    "checked": false,
    "variation": true,
    "colors": [
      { "id": 393, "name": "イエロー", "checked": false, "parentId": 392 },
      { "id": 394, "name": "ブラック", "checked": false, "parentId": 392 },
      { "id": 395, "name": "レッド", "checked": false, "parentId": 392 },
      { "id": 396, "name": "ブルー", "checked": false, "parentId": 392 },
      { "id": 397, "name": "ライトブルー", "checked": false, "parentId": 392 },
      { "id": 398, "name": "グリーン", "checked": false, "parentId": 392 },
      { "id": 399, "name": "オレンジ", "checked": false, "parentId": 392 },
      { "id": 400, "name": "ホワイト", "checked": false, "parentId": 392 }
    ]
  },
  {
    "id": 401,
    "name": "ししゅうのキャミソール",
    "checked": false,
    "variation": true,
    "colors": [
      { "id": 402, "name": "レッド", "checked": false, "parentId": 401 },
      { "id": 403, "name": "パープル", "checked": false, "parentId": 402 },
      { "id": 404, "name": "ブルー", "checked": false, "parentId": 403 },
      { "id": 405, "name": "ピンク", "checked": false, "parentId": 404 },
      { "id": 406, "name": "グリーン", "checked": false, "parentId": 405 },
      { "id": 407, "name": "ベージュ", "checked": false, "parentId": 406 },
      { "id": 408, "name": "ネイビー", "checked": false, "parentId": 407 }
    ]
  },
  {
    "id": 409,
    "name": "しましまTシャツ",
    "checked": false,
    "variation": true,
    "colors": [
      { "id": 410, "name": "タイガー", "checked": false, "parentId": 409 },
      { "id": 411, "name": "ゼブラ", "checked": false, "parentId": 409 }
    ]
  },
  {
    "id": 412,
    "name": "ジャージ",
    "checked": false,
    "variation": true,
    "colors": [
      { "id": 413, "name": "レッド", "checked": false, "parentId": 412 },
      { "id": 414, "name": "グリーン", "checked": false, "parentId": 412 },
      { "id": 415, "name": "ブラック", "checked": false, "parentId": 412 },
      { "id": 416, "name": "ブルー", "checked": false, "parentId": 412 },
      { "id": 417, "name": "ワインレッド", "checked": false, "parentId": 412 },
      { "id": 418, "name": "ネイビー", "checked": false, "parentId": 412 }
    ]
  },
  {
    "id": 419,
    "name": "じゅうきしのふく",
    "checked": false,
    "variation": true,
    "colors": [
      { "id": 420, "name": "ブルー", "checked": false, "parentId": 419 },
      { "id": 421, "name": "レッド", "checked": false, "parentId": 419 },
      { "id": 422, "name": "グリーン", "checked": false, "parentId": 419 }
    ]
  },
  {
    "id": 423,
    "name": "ジレコーデTシャツ",
    "checked": false,
    "variation": true,
    "colors": [
      { "id": 424, "name": "ブラック", "checked": false, "parentId": 423 },
      { "id": 425, "name": "ブルー", "checked": false, "parentId": 423 },
      { "id": 426, "name": "レッド", "checked": false, "parentId": 423 },
      { "id": 427, "name": "グレー", "checked": false, "parentId": 423 }
    ]
  },
  {
    "id": 428,
    "name": "シンプルドットのTシャツ",
    "checked": false,
    "variation": true,
    "colors": [
      { "id": 429, "name": "イエロー", "checked": false, "parentId": 428 },
      { "id": 430, "name": "ライトブルー", "checked": false, "parentId": 428 },
      { "id": 431, "name": "レッド", "checked": false, "parentId": 428 },
      { "id": 432, "name": "グリーン", "checked": false, "parentId": 428 },
      { "id": 433, "name": "ブラック", "checked": false, "parentId": 428 }
    ]
  },
  {
    "id": 434,
    "name": "シンプルなトレーナー",
    "checked": false,
    "variation": true,
    "colors": [
      { "id": 435, "name": "グレー", "checked": false, "parentId": 434 },
      { "id": 436, "name": "グリーン", "checked": false, "parentId": 434 },
      { "id": 437, "name": "イエロー", "checked": false, "parentId": 434 },
      { "id": 438, "name": "パープル", "checked": false, "parentId": 434 },
      { "id": 439, "name": "レッド", "checked": false, "parentId": 434 },
      { "id": 440, "name": "ブルー", "checked": false, "parentId": 434 }
    ]
  },
  {
    "id": 441,
    "name": "シンプルなニット",
    "checked": false,
    "variation": true,
    "colors": [
      { "id": 442, "name": "ホワイト", "checked": false, "parentId": 441 },
      { "id": 443, "name": "ブラック", "checked": false, "parentId": 441 },
      { "id": 444, "name": "キャメル", "checked": false, "parentId": 441 }
    ]
  },
  {
    "id": 445,
    "name": "シンプルなパーカー",
    "checked": false,
    "variation": true,
    "colors": [
      { "id": 446, "name": "グレー", "checked": false, "parentId": 445 },
      { "id": 447, "name": "レッド", "checked": false, "parentId": 445 },
      { "id": 448, "name": "グリーン", "checked": false, "parentId": 445 },
      { "id": 449, "name": "ブルー", "checked": false, "parentId": 445 },
      { "id": 450, "name": "イエロー", "checked": false, "parentId": 445 },
      { "id": 451, "name": "ピンク", "checked": false, "parentId": 445 },
      { "id": 452, "name": "ライトブルー", "checked": false, "parentId": 445 },
      { "id": 453, "name": "ブラック", "checked": false, "parentId": 445 }
    ]
  },
  {
    "id": 454,
    "name": "シンプルフリルキャミソール",
    "checked": false,
    "variation": true,
    "colors": [
      { "id": 455, "name": "イエロー", "checked": false, "parentId": 454 },
      { "id": 456, "name": "ピンク", "checked": false, "parentId": 454 },
      { "id": 457, "name": "オレンジ", "checked": false, "parentId": 454 },
      { "id": 458, "name": "ブルー", "checked": false, "parentId": 454 },
      { "id": 459, "name": "グリーン", "checked": false, "parentId": 454 },
      { "id": 460, "name": "ライトブルー", "checked": false, "parentId": 454 },
      { "id": 461, "name": "レッド", "checked": false, "parentId": 454 },
      { "id": 462, "name": "パープル", "checked": false, "parentId": 454 }
    ]
  },
  {
    "id": 463,
    "name": "スーツ",
    "checked": false,
    "variation": true,
    "colors": [
      { "id": 464, "name": "ブラック", "checked": false, "parentId": 463 },
      { "id": 465, "name": "グレー", "checked": false, "parentId": 463 },
      { "id": 466, "name": "ブルー", "checked": false, "parentId": 463 },
      { "id": 467, "name": "ワインレッド", "checked": false, "parentId": 463 },
      { "id": 468, "name": "ネイビー", "checked": false, "parentId": 463 }
    ]
  },
  {
    "id": 469,
    "name": "スキーウェア",
    "checked": false,
    "variation": true,
    "colors": [
      { "id": 470, "name": "ブルー", "checked": false, "parentId": 469 },
      { "id": 471, "name": "ライトブルー", "checked": false, "parentId": 469 },
      { "id": 472, "name": "パープル", "checked": false, "parentId": 469 },
      { "id": 473, "name": "グリーン", "checked": false, "parentId": 469 },
      { "id": 474, "name": "レッド", "checked": false, "parentId": 469 },
      { "id": 475, "name": "ルージュ", "checked": false, "parentId": 469 }
    ]
  },
  {
    "id": 476,
    "name": "スキーダウンジャケット",
    "checked": false,
    "variation": true,
    "colors": [
      { "id": 477, "name": "レッド×イエロー", "checked": false, "parentId": 476 },
      { "id": 478, "name": "ブルー×グリーン", "checked": false, "parentId": 476 },
      { "id": 479, "name": "ネイビー×ブルー", "checked": false, "parentId": 476 },
      { "id": 480, "name": "ネイビー×レッド", "checked": false, "parentId": 476 }
    ]
  },
  {
    "id": 481,
    "name": "すこやかなセーター",
    "checked": false,
    "variation": true,
    "colors": [
      { "id": 482, "name": "イエロー", "checked": false, "parentId": 481 },
      { "id": 483, "name": "ライトブルー", "checked": false, "parentId": 481 },
      { "id": 484, "name": "パープル", "checked": false, "parentId": 481 },
      { "id": 485, "name": "ピンク", "checked": false, "parentId": 481 }
    ]
  },
  {
    "id": 486,
    "name": "スタジャン",
    "checked": false,
    "variation": true,
    "colors": [
      { "id": 487, "name": "ブルー", "checked": false, "parentId": 486 },
      { "id": 488, "name": "レッド", "checked": false, "parentId": 486 },
      { "id": 489, "name": "グリーン", "checked": false, "parentId": 486 },
      { "id": 490, "name": "ベージュ", "checked": false, "parentId": 486 }
    ]
  },
  {
    "id": 491,
    "name": "スタッフのふく",
    "checked": false,
    "variation": true,
    "colors": [
      { "id": 492, "name": "ブルー", "checked": false, "parentId": 491 },
      { "id": 493, "name": "イエロー", "checked": false, "parentId": 491 },
      { "id": 494, "name": "ピンク", "checked": false, "parentId": 491 }
    ]
  },
  {
    "id": 495,
    "name": "ステンカラーコート",
    "checked": false,
    "variation": true,
    "colors": [
      { "id": 496, "name": "ライトブルー", "checked": false, "parentId": 495 },
      { "id": 497, "name": "ベージュ", "checked": false, "parentId": 495 },
      { "id": 498, "name": "ブラウン", "checked": false, "parentId": 495 },
      { "id": 499, "name": "ピンク", "checked": false, "parentId": 495 }
    ]
  },
  {
    "id": 500,
    "name": "スノーセーター",
    "checked": false,
    "variation": true,
    "colors": [
      { "id": 501, "name": "グレー", "checked": false, "parentId": 500 },
      { "id": 502, "name": "ブルー", "checked": false, "parentId": 500 },
      { "id": 503, "name": "ブラック", "checked": false, "parentId": 500 }
    ]
  },
  {
    "id": 504,
    "name": "スパイダーなTシャツ",
    "checked": false,
    "variation": false
  },
  {
    "id": 505,
    "name": "スペースパーカー",
    "checked": false,
    "variation": true,
    "colors": [
      { "id": 506, "name": "ブルー", "checked": false, "parentId": 505 },
      { "id": 507, "name": "パープル", "checked": false, "parentId": 505 }
    ]
  },
  {
    "id": 508,
    "name": "スポーツジャージ",
    "checked": false,
    "variation": true,
    "colors": [
      { "id": 509, "name": "ネイビー", "checked": false, "parentId": 508 },
      { "id": 510, "name": "グレー", "checked": false, "parentId": 508 },
      { "id": 511, "name": "ホワイト", "checked": false, "parentId": 508 },
      { "id": 512, "name": "レッド", "checked": false, "parentId": 508 },
      { "id": 513, "name": "ライトブルー", "checked": false, "parentId": 508 },
      { "id": 514, "name": "グリーン", "checked": false, "parentId": 508 },
      { "id": 515, "name": "ブルー", "checked": false, "parentId": 508 }
    ]
  },
  {
    "id": 516,
    "name": "スモック",
    "checked": false,
    "variation": true,
    "colors": [
      { "id": 517, "name": "チューリップ", "checked": false, "parentId": 516 },
      { "id": 518, "name": "ヒヨコ", "checked": false, "parentId": 516 },
      { "id": 519, "name": "サクラ", "checked": false, "parentId": 516 },
      { "id": 520, "name": "カエル", "checked": false, "parentId": 516 }
    ]
  },
  {
    "id": 521,
    "name": "スリムニット",
    "checked": false,
    "variation": true,
    "colors": [
      { "id": 522, "name": "ブラック", "checked": false, "parentId": 521 },
      { "id": 523, "name": "ベージュ", "checked": false, "parentId": 521 },
      { "id": 524, "name": "グレー", "checked": false, "parentId": 521 }
    ]
  },
  {
    "id": 525,
    "name": "セーラーシャツ",
    "checked": false,
    "variation": true,
    "colors": [
      { "id": 526, "name": "ネイビー", "checked": false, "parentId": 525 },
      { "id": 527, "name": "ライトブルー", "checked": false, "parentId": 525 },
      { "id": 528, "name": "ホワイト", "checked": false, "parentId": 525 }
    ]
  },
  {
    "id": 529,
    "name": "そうがんきょうつきベスト",
    "checked": false,
    "variation": false
  },
  {
    "id": 530,
    "name": "そでなしGジャン",
    "checked": false,
    "variation": true,
    "colors": [
      { "id": 531, "name": "ウォッシュ", "checked": false, "parentId": 530 },
      { "id": 532, "name": "ブルー", "checked": false, "parentId": 530 },
      { "id": 533, "name": "ネイビー", "checked": false, "parentId": 530 },
      { "id": 534, "name": "ブラック", "checked": false, "parentId": 530 },
      { "id": 535, "name": "ホワイト", "checked": false, "parentId": 530 }
    ]
  },
  {
    "id": 536,
    "name": "たいそうふく",
    "checked": false,
    "variation": true,
    "colors": [
      { "id": 537, "name": "レッド", "checked": false, "parentId": 536 },
      { "id": 538, "name": "ブルー", "checked": false, "parentId": 536 },
      { "id": 539, "name": "グリーン", "checked": false, "parentId": 536 },
      { "id": 540, "name": "ブラック", "checked": false, "parentId": 536 }
    ]
  },
  {
    "id": 541,
    "name": "タイダイTシャツ",
    "checked": false,
    "variation": false
  },
  {
    "id": 542,
    "name": "ダイナーのエプロン",
    "checked": false,
    "variation": true,
    "colors": [
      { "id": 543, "name": "ピンク", "checked": false, "parentId": 542 },
      { "id": 544, "name": "レッド", "checked": false, "parentId": 542 },
      { "id": 545, "name": "ブルー", "checked": false, "parentId": 542 },
      { "id": 546, "name": "イエロー", "checked": false, "parentId": 542 },
      { "id": 547, "name": "エメラルド", "checked": false, "parentId": 542 },
      { "id": 548, "name": "クリーム", "checked": false, "parentId": 542 },
      { "id": 549, "name": "ブラック", "checked": false, "parentId": 542 }
    ]
  },
  {
    "id": 550,
    "name": "ダウンジャケット",
    "checked": false,
    "variation": true,
    "colors": [
      { "id": 551, "name": "ブルー", "checked": false, "parentId": 550 },
      { "id": 552, "name": "ブラック", "checked": false, "parentId": 550 },
      { "id": 553, "name": "レッド", "checked": false, "parentId": 550 },
      { "id": 554, "name": "ホワイト", "checked": false, "parentId": 550 },
      { "id": 555, "name": "グリーン", "checked": false, "parentId": 550 },
      { "id": 556, "name": "イエロー", "checked": false, "parentId": 550 },
      { "id": 557, "name": "オレンジ", "checked": false, "parentId": 550 },
      { "id": 558, "name": "ライム", "checked": false, "parentId": 550 }
    ]
  },
  {
    "id": 559,
    "name": "ダウンベスト",
    "checked": false,
    "variation": true,
    "colors": [
      { "id": 560, "name": "ネイビー", "checked": false, "parentId": 559 },
      { "id": 561, "name": "キャメル", "checked": false, "parentId": 559 },
      { "id": 562, "name": "ブルー", "checked": false, "parentId": 559 },
      { "id": 563, "name": "オリーブ", "checked": false, "parentId": 559 },
      { "id": 564, "name": "レッド", "checked": false, "parentId": 559 }
    ]
  },
  {
    "id": 565,
    "name": "タカのスカジャン",
    "checked": false,
    "variation": false
  },
  {
    "id": 566,
    "name": "タキシード",
    "checked": false,
    "variation": true,
    "colors": [
      { "id": 567, "name": "ブラック", "checked": false, "parentId": 566 },
      { "id": 568, "name": "グレー", "checked": false, "parentId": 566 },
      { "id": 569, "name": "ホワイト", "checked": false, "parentId": 566 }
    ]
  },
  {
    "id": 570,
    "name": "たきのうベスト",
    "checked": false,
    "variation": true,
    "colors": [
      { "id": 571, "name": "ベージュ", "checked": false, "parentId": 570 },
      { "id": 572, "name": "グレー", "checked": false, "parentId": 570 },
      { "id": 573, "name": "カーキ", "checked": false, "parentId": 570 }
    ]
  },
  {
    "id": 574,
    "name": "ダッフルコート",
    "checked": false,
    "variation": true,
    "colors": [
      { "id": 575, "name": "ネイビー", "checked": false, "parentId": 574 },
      { "id": 576, "name": "レッド", "checked": false, "parentId": 574 },
      { "id": 577, "name": "ベージュ", "checked": false, "parentId": 574 },
      { "id": 578, "name": "グレー", "checked": false, "parentId": 574 }
    ]
  },
  {
    "id": 579,
    "name": "たぬきかいはつTシャツ",
    "checked": false,
    "variation": false
  },
  {
    "id": 580,
    "name": "たぬきかいはつアロハ",
    "checked": false,
    "variation": false
  },
  {
    "id": 581,
    "name": "たぬきかいはつアロハ・グリーン",
    "checked": false,
    "variation": false
  },
  {
    "id": 582,
    "name": "たぬきかいはつアロハ・コーラル",
    "checked": false,
    "variation": false
  },
  {
    "id": 583,
    "name": "たぬきかいはつブルゾン",
    "checked": false,
    "variation": false
  },
  {
    "id": 584,
    "name": "ダブレット",
    "checked": false,
    "variation": true,
    "colors": [
      { "id": 585, "name": "ブラック", "checked": false, "parentId": 584 },
      { "id": 586, "name": "ブルー", "checked": false, "parentId": 584 },
      { "id": 587, "name": "グリーン", "checked": false, "parentId": 584 },
      { "id": 588, "name": "レッド", "checked": false, "parentId": 584 }
    ]
  },
  {
    "id": 589,
    "name": "ダメージニット",
    "checked": false,
    "variation": true,
    "colors": [
      { "id": 590, "name": "グリーン", "checked": false, "parentId": 589 },
      { "id": 591, "name": "ブラック", "checked": false, "parentId": 589 },
      { "id": 592, "name": "ベージュ", "checked": false, "parentId": 589 },
      { "id": 593, "name": "ピンク", "checked": false, "parentId": 589 }
    ]
  },
  {
    "id": 594,
    "name": "タンクトップ",
    "checked": false,
    "variation": true,
    "colors": [
      { "id": 595, "name": "ブラック", "checked": false, "parentId": 594 },
      { "id": 596, "name": "ホワイト", "checked": false, "parentId": 594 },
      { "id": 597, "name": "ブラウン", "checked": false, "parentId": 594 },
      { "id": 598, "name": "レッド", "checked": false, "parentId": 594 },
      { "id": 599, "name": "ネイビー", "checked": false, "parentId": 594 }
    ]
  },
  {
    "id": 600,
    "name": "タンクトップチュニック",
    "checked": false,
    "variation": true,
    "colors": [
      { "id": 601, "name": "ホワイト", "checked": false, "parentId": 600 },
      { "id": 602, "name": "イエロー", "checked": false, "parentId": 600 },
      { "id": 603, "name": "ピンク", "checked": false, "parentId": 600 },
      { "id": 604, "name": "ミント", "checked": false, "parentId": 600 }
    ]
  },
  {
    "id": 605,
    "name": "たんけんふく",
    "checked": false,
    "variation": true,
    "colors": [
      { "id": 606, "name": "キャメル", "checked": false, "parentId": 605 },
      { "id": 607, "name": "カーキ", "checked": false, "parentId": 605 },
      { "id": 608, "name": "ベージュ", "checked": false, "parentId": 605 },
      { "id": 609, "name": "ブルー", "checked": false, "parentId": 605 }
    ]
  },
  {
    "id": 610,
    "name": "ダンスジャージ",
    "checked": false,
    "variation": true,
    "colors": [
      { "id": 611, "name": "ブラック", "checked": false, "parentId": 610 },
      { "id": 612, "name": "ホワイト", "checked": false, "parentId": 610 },
      { "id": 613, "name": "パープル", "checked": false, "parentId": 610 },
      { "id": 614, "name": "レッド", "checked": false, "parentId": 610 }
    ]
  },
  {
    "id": 615,
    "name": "チェスターコート",
    "checked": false,
    "variation": true,
    "colors": [
      { "id": 616, "name": "キャメル", "checked": false, "parentId": 615 },
      { "id": 617, "name": "ブラウン", "checked": false, "parentId": 615 },
      { "id": 618, "name": "ブラック", "checked": false, "parentId": 615 },
      { "id": 619, "name": "グレー", "checked": false, "parentId": 615 }
    ]
  },
  {
    "id": 620,
    "name": "チェックのチェスターコート",
    "checked": false,
    "variation": true,
    "colors": [
      { "id": 621, "name": "ブラウン", "checked": false, "parentId": 620 },
      { "id": 622, "name": "グリーン", "checked": false, "parentId": 620 },
      { "id": 623, "name": "ブルー", "checked": false, "parentId": 620 },
      { "id": 624, "name": "グレー", "checked": false, "parentId": 620 }
    ]
  },
  {
    "id": 625,
    "name": "チェックマフラーつきセーター",
    "checked": false,
    "variation": true,
    "colors": [
      { "id": 626, "name": "ホワイト", "checked": false, "parentId": 625 },
      { "id": 627, "name": "グレー", "checked": false, "parentId": 625 },
      { "id": 628, "name": "ブラウン", "checked": false, "parentId": 625 },
      { "id": 629, "name": "キャメル", "checked": false, "parentId": 625 }
    ]
  },
  {
    "id": 630,
    "name": "ちどりのカーディガン",
    "checked": false,
    "variation": true,
    "colors": [
      { "id": 631, "name": "レッド", "checked": false, "parentId": 630 },
      { "id": 632, "name": "ブラック", "checked": false, "parentId": 630 },
      { "id": 633, "name": "グリーン", "checked": false, "parentId": 630 }
    ]
  },
  {
    "id": 634,
    "name": "チマヨベスト",
    "checked": false,
    "variation": true,
    "colors": [
      { "id": 635, "name": "ネイビー", "checked": false, "parentId": 634 },
      { "id": 636, "name": "レッド", "checked": false, "parentId": 634 },
      { "id": 637, "name": "ホワイト", "checked": false, "parentId": 634 },
      { "id": 638, "name": "ライトブルー", "checked": false, "parentId": 634 }
    ]
  },
  {
    "id": 639,
    "name": "チャイナふく",
    "checked": false,
    "variation": true,
    "colors": [
      { "id": 640, "name": "グリーン", "checked": false, "parentId": 639 },
      { "id": 641, "name": "レッド", "checked": false, "parentId": 639 },
      { "id": 642, "name": "ブルー", "checked": false, "parentId": 639 },
      { "id": 643, "name": "イエロー", "checked": false, "parentId": 639 },
      { "id": 644, "name": "ブラック", "checked": false, "parentId": 639 }
    ]
  },
  {
    "id": 645,
    "name": "チャオTシャツ",
    "checked": false,
    "variation": false
  },
  {
    "id": 646,
    "name": "チューブトップ",
    "checked": false,
    "variation": true,
    "colors": [
      { "id": 647, "name": "グリーン", "checked": false, "parentId": 646 },
      { "id": 648, "name": "レッド", "checked": false, "parentId": 646 },
      { "id": 649, "name": "イエロー", "checked": false, "parentId": 646 },
      { "id": 650, "name": "ダークグレー", "checked": false, "parentId": 646 },
      { "id": 651, "name": "パープル", "checked": false, "parentId": 646 },
      { "id": 652, "name": "ブルー", "checked": false, "parentId": 646 },
      { "id": 653, "name": "ダークレッド", "checked": false, "parentId": 646 }
    ]
  },
  {
    "id": 654,
    "name": "チュニックシャツ",
    "checked": false,
    "variation": true,
    "colors": [
      { "id": 655, "name": "パープル", "checked": false, "parentId": 654 },
      { "id": 656, "name": "ブルー", "checked": false, "parentId": 654 },
      { "id": 657, "name": "ミント", "checked": false, "parentId": 654 },
      { "id": 658, "name": "ピンク", "checked": false, "parentId": 654 },
      { "id": 659, "name": "ホワイト", "checked": false, "parentId": 654 },
      { "id": 660, "name": "イエロー", "checked": false, "parentId": 654 }
    ]
  },
  {
    "id": 661,
    "name": "チョッキつきワイシャツ",
    "checked": false,
    "variation": true,
    "colors": [
      { "id": 662, "name": "ベージュ", "checked": false, "parentId": 661 },
      { "id": 663, "name": "ネイビー", "checked": false, "parentId": 661 },
      { "id": 664, "name": "グレー", "checked": false, "parentId": 661 },
      { "id": 665, "name": "ホワイト", "checked": false, "parentId": 661 }
    ]
  },
  {
    "id": 666,
    "name": "ツートンのエリつきシャツ",
    "checked": false,
    "variation": true,
    "colors": [
      { "id": 667, "name": "ブルー", "checked": false, "parentId": 666 },
      { "id": 668, "name": "レッド", "checked": false, "parentId": 666 },
      { "id": 669, "name": "グリーン", "checked": false, "parentId": 666 },
      { "id": 670, "name": "パープル", "checked": false, "parentId": 666 },
      { "id": 671, "name": "イエロー", "checked": false, "parentId": 666 },
      { "id": 672, "name": "グレー", "checked": false, "parentId": 666 }
    ]
  },
  {
    "id": 673,
    "name": "ツイードジャケット",
    "checked": false,
    "variation": true,
    "colors": [
      { "id": 674, "name": "ブラウン", "checked": false, "parentId": 673 },
      { "id": 675, "name": "ブルー", "checked": false, "parentId": 673 },
      { "id": 676, "name": "ベージュ", "checked": false, "parentId": 673 },
      { "id": 677, "name": "ワインレッド", "checked": false, "parentId": 673 },
      { "id": 678, "name": "グリーン", "checked": false, "parentId": 673 },
      { "id": 679, "name": "ピンク", "checked": false, "parentId": 673 }
    ]
  },
  {
    "id": 680,
    "name": "ツイードベスト",
    "checked": false,
    "variation": true,
    "colors": [
      { "id": 681, "name": "グリーン", "checked": false, "parentId": 680 },
      { "id": 682, "name": "レッド", "checked": false, "parentId": 680 },
      { "id": 683, "name": "ネイビー", "checked": false, "parentId": 680 }
    ]
  },
  {
    "id": 684,
    "name": "つつましいニット",
    "checked": false,
    "variation": true,
    "colors": [
      { "id": 685, "name": "パープル", "checked": false, "parentId": 684 },
      { "id": 686, "name": "ブラウン", "checked": false, "parentId": 684 },
      { "id": 687, "name": "グリーン", "checked": false, "parentId": 684 },
      { "id": 688, "name": "ブルー", "checked": false, "parentId": 684 }
    ]
  },
  {
    "id": 689,
    "name": "つりジャケット",
    "checked": false,
    "variation": true,
    "colors": [
      { "id": 690, "name": "レッド", "checked": false, "parentId": 689 },
      { "id": 691, "name": "ブルー", "checked": false, "parentId": 689 },
      { "id": 692, "name": "オレンジ", "checked": false, "parentId": 689 },
      { "id": 693, "name": "パープル", "checked": false, "parentId": 689 },
      { "id": 694, "name": "ブラック", "checked": false, "parentId": 689 },
      { "id": 695, "name": "ピンク", "checked": false, "parentId": 689 },
      { "id": 696, "name": "グリーン", "checked": false, "parentId": 689 },
      { "id": 697, "name": "カーキ", "checked": false, "parentId": 689 }
    ]
  },
  {
    "id": 698,
    "name": "テーラードジャケット",
    "checked": false,
    "variation": true,
    "colors": [
      { "id": 699, "name": "グレー", "checked": false, "parentId": 698 },
      { "id": 700, "name": "ブラック", "checked": false, "parentId": 698 },
      { "id": 701, "name": "ネイビー", "checked": false, "parentId": 698 },
      { "id": 702, "name": "ベージュ", "checked": false, "parentId": 698 },
      { "id": 703, "name": "グリーン", "checked": false, "parentId": 698 }
    ]
  },
  {
    "id": 704,
    "name": "てづくりのマント",
    "checked": false,
    "variation": false
  },
  {
    "id": 705,
    "name": "テニスセーター",
    "checked": false,
    "variation": true,
    "colors": [
      { "id": 706, "name": "アイボリー", "checked": false, "parentId": 705 },
      { "id": 707, "name": "グリーン", "checked": false, "parentId": 705 },
      { "id": 708, "name": "ブラウン", "checked": false, "parentId": 705 },
      { "id": 709, "name": "レッド", "checked": false, "parentId": 705 }
    ]
  },
  {
    "id": 710,
    "name": "デニムジャケット",
    "checked": false,
    "variation": true,
    "colors": [
      { "id": 711, "name": "ブルー", "checked": false, "parentId": 710 },
      { "id": 712, "name": "ライトブルー", "checked": false, "parentId": 710 },
      { "id": 713, "name": "ネイビー", "checked": false, "parentId": 710 },
      { "id": 714, "name": "ブラック", "checked": false, "parentId": 710 },
      { "id": 715, "name": "ホワイト", "checked": false, "parentId": 710 }
    ]
  },
  {
    "id": 716,
    "name": "デンジャラスなタンクトップ",
    "checked": false,
    "variation": false
  },
  {
    "id": 717,
    "name": "ドーリーシャツ",
    "checked": false,
    "variation": true,
    "colors": [
      { "id": 718, "name": "ピンク", "checked": false, "parentId": 717 },
      { "id": 719, "name": "ブルー", "checked": false, "parentId": 717 },
      { "id": 720, "name": "イエロー", "checked": false, "parentId": 717 },
      { "id": 721, "name": "パープル", "checked": false, "parentId": 717 }
    ]
  },
  {
    "id": 722,
    "name": "とうじのセーター",
    "checked": false,
    "variation": false
  },
  {
    "id": 723,
    "name": "ドクロTシャツ",
    "checked": false,
    "variation": true,
    "colors": [
      { "id": 724, "name": "ブラック", "checked": false, "parentId": 723 },
      { "id": 725, "name": "ベージュ", "checked": false, "parentId": 723 },
      { "id": 726, "name": "パープル", "checked": false, "parentId": 723 }
    ]
  },
  {
    "id": 727,
    "name": "トナカイセーター",
    "checked": false,
    "variation": true,
    "colors": [
      { "id": 728, "name": "グリーン", "checked": false, "parentId": 727 },
      { "id": 729, "name": "ブラウン", "checked": false, "parentId": 727 },
      { "id": 730, "name": "レッド", "checked": false, "parentId": 727 }
    ]
  },
  {
    "id": 731,
    "name": "ドラゴンのスカジャン",
    "checked": false,
    "variation": false
  },
  {
    "id": 732,
    "name": "トラのスカジャン",
    "checked": false,
    "variation": false
  },
  {
    "id": 733,
    "name": "トレンチコート",
    "checked": false,
    "variation": true,
    "colors": [
      { "id": 734, "name": "ベージュ", "checked": false, "parentId": 733 },
      { "id": 735, "name": "ライトブルー", "checked": false, "parentId": 733 },
      { "id": 736, "name": "レッド", "checked": false, "parentId": 733 },
      { "id": 737, "name": "オレンジ", "checked": false, "parentId": 733 },
      { "id": 738, "name": "ネイビー", "checked": false, "parentId": 733 }
    ]
  },
  {
    "id": 739,
    "name": "トレンディーなふく",
    "checked": false,
    "variation": true,
    "colors": [
      { "id": 740, "name": "ピンク", "checked": false, "parentId": 739 },
      { "id": 741, "name": "ブルー", "checked": false, "parentId": 739 },
      { "id": 742, "name": "イエロー", "checked": false, "parentId": 739 },
      { "id": 743, "name": "グリーン", "checked": false, "parentId": 739 },
      { "id": 744, "name": "グレー", "checked": false, "parentId": 739 }
    ]
  }
]